elephas_wheel/__init__.py
elephas_wheel/__main__.py
elephas_wheel/_setuptools_logging.py
elephas_wheel/bdist_wheel.py
elephas_wheel/macosx_libfile.py
elephas_wheel/metadata.py
elephas_wheel/util.py
elephas_wheel/wheelfile.py
elephas_wheel/cli/__init__.py
elephas_wheel/cli/convert.py
elephas_wheel/cli/pack.py
elephas_wheel/cli/unpack.py
elephas_wheel/vendored/__init__.py
elephas_wheel/vendored/packaging/__init__.py
elephas_wheel/vendored/packaging/_manylinux.py
elephas_wheel/vendored/packaging/_musllinux.py
elephas_wheel/vendored/packaging/tags.py
elephas_wheel-0.0.1.dist-info/LICENSE.txt
elephas_wheel-0.0.1.dist-info/METADATA
elephas_wheel-0.0.1.dist-info/WHEEL
elephas_wheel-0.0.1.dist-info/entry_points.txt
elephas_wheel-0.0.1.dist-info/top_level.txt
elephas_wheel-0.0.1.dist-info/RECORD
